[{"music":"https://kth-studio.github.io/Oxxxymiron/miXXXtape/Чёртово%20колесо/music.mp3",
"image":"https://kth-studio.github.io/Oxxxymiron/miXXXtape/image.jpg",
"previous":"https://kth-studio.github.io/Oxxxymiron/miXXXtape/Мой%20менталитет/link.json",
"next":"https://kth-studio.github.io/Oxxxymiron/miXXXtape/Нет%20связи/link.json",
"artist":"Oxxxymiron",
"artist_uri":"[{\"info_en\":\"Artist\",\"info_ru\":\"Артист\",\"info_de\":\"Interpret:in\",\"name\":\"Oxxxymiron\",\"image\":\"https://kth-studio.github.io/Oxxxymiron/image.jpg\",\"link\":\"https://kth-studio.github.io/Oxxxymiron/link.json\"}]",
"album":"miXXXtape",
"album_uri":"https://kth-studio.github.io/Oxxxymiron/miXXXtape/link.json",
"name":"Чёртово колесо",
"explicit":"yes",
"text":"[{\"text\":\"Я помню, как мне оперировали полипы в носу\nПомню, как все мастурбировали на клипы Алсу\nНо я не помню, чтобы вы были с нами, вы выбыли\nЗначит я на ваши могильные плиты нассу\nИ ты не Alfa Romeo, ты лишь бета-Джульетта\nВаш рэп — это старая школа, ведь ваши парты — фанера\nТы рэпера видишь, что дороже вам и круче нет\nУ тебя имидж отмороженного Gucci Mane\nНам бы не сторчаться да не сесть\nУ тебя цели стукача, сын — достучаться до небес\nИ вы меня так долго ждали — это для вкуса на пробу\nУ тебя прямая связь с ментами — мусоропровод\nВот он, наполовину ботан и наполовину Вотан\nКак мата лавина в лоб и лопата в могилу хопа\nЯ лапал вагины опытных дам под хава нагила, На-На и la Vida Loca\n\nМимо ухоженных газонов старый зонт вынув\n\n\",\"written\":\"Мирон Фёдоров\"}]"}]